MANIFEST.in
README.md
setup.py
src/microscan/__init__.py
src/microscan/config.py
src/microscan/driver.py
src/microscan.egg-info/PKG-INFO
src/microscan.egg-info/SOURCES.txt
src/microscan.egg-info/dependency_links.txt
src/microscan.egg-info/entry_points.txt
src/microscan.egg-info/requires.txt
src/microscan.egg-info/top_level.txt
src/microscan/tools/__init__.py
src/microscan/tools/server.py