Metadata-Version: 1.1
Name: microscan
Version: 0.0.2
Summary: Python driver from Microscan barcode readers
Home-page: https://github.com/jonemo/microscan-driver
Author: Jonas Neubert
Author-email: jn@jonasneubert.com
License: MIT
Platform: UNKNOWN
Classifier: Development Status :: 1 - Planning
Classifier: Environment :: No Input/Output (Daemon)
Classifier: Intended Audience :: Developers
Classifier: License :: OSI Approved :: MIT License
Classifier: Programming Language :: Python :: 2
Classifier: Programming Language :: Python :: 2.7
Classifier: Programming Language :: Python :: 3
Classifier: Programming Language :: Python :: 3.3
Classifier: Programming Language :: Python :: 3.4
Classifier: Programming Language :: Python :: 3.5
Classifier: Topic :: System :: Hardware :: Hardware Drivers
